mylogging/__init__.py
mylogging/config_module.py
mylogging/helpers.py
mylogging/internal_module.py
mylogging/log_functions.py
mylogging/str_formating.py
mylogging/colors/__init__.py
mylogging/colors/colors_module.py
mylogging/misc/__init__.py
mylogging/misc/misc_module.py
mylogging/my_logging/__init__.py
mylogging/my_logging/logger_module.py
mylogging/my_traceback/__init__.py
mylogging/my_traceback/my_traceback_module.py
mylogging/my_warnings/__init__.py
mylogging/my_warnings/warnings_module.py
mylogging-4.0.6.dist-info/LICENSE
mylogging-4.0.6.dist-info/METADATA
mylogging-4.0.6.dist-info/WHEEL
mylogging-4.0.6.dist-info/top_level.txt
mylogging-4.0.6.dist-info/RECORD
