Metadata-Version: 2.1
Name: mylogging
Version: 4.0.6
Summary: Small library for printing warnings and creating logs.
Home-page: https://github.com/Malachov/mylogging
Author: Daniel Malachov
Author-email: malachovd@seznam.cz
License: mit
Project-URL: Documentation, https://mylogging.readthedocs.io/
Project-URL: Home, https://github.com/Malachov/mylogging
Platform: any
Classifier: Programming Language :: Python
Classifier: Development Status :: 4 - Beta
Classifier: Programming Language :: Python :: 3.7
Classifier: Programming Language :: Python :: 3.8
Classifier: Programming Language :: Python :: 3.9
Classifier: Programming Language :: Python :: 3.10
Classifier: Programming Language :: Python :: 3.11
Classifier: Natural Language :: English
Classifier: Environment :: Other Environment
Classifier: License :: OSI Approved :: MIT License
Classifier: Operating System :: OS Independent
Classifier: Topic :: Software Development :: Libraries :: Python Modules
Classifier: Topic :: Software Development :: Libraries :: Application Frameworks
Classifier: Intended Audience :: Developers
Classifier: Intended Audience :: Education
Requires-Python: >=3.7
License-File: LICENSE
Requires-Dist: pygments
Requires-Dist: typing-extensions
Requires-Dist: typeguard
